n_link_simulator.libs/libgcc_s-a04fdf82.so.1
n_link_simulator.libs/libstdc++-a9383cce.so.6.0.28
n_link_simulator-0.1.1.dist-info/top_level.txt
n_link_simulator-0.1.1.dist-info/WHEEL
n_link_simulator-0.1.1.dist-info/METADATA
n_link_simulator-0.1.1.dist-info/RECORD
n_link_sim/double_link.cpython-37m-x86_64-linux-gnu.so
n_link_sim/__init__.py
n_link_sim/quad_link.cpython-37m-x86_64-linux-gnu.so
