Metadata-Version: 2.1
Name: n-link-simulator
Version: 0.1.1
Summary: Simulators for double and quad link dynamics, taken from pypost toolbox
Home-page: https://github.com/sebimarkgraf/n_link_simulator
Author: Sebastian Markgraf
Author-email: sebastian-markgraf@t-online.de
License: UNKNOWN
Platform: UNKNOWN
Requires-Python: >=3.6
Requires-Dist: numpy
Provides-Extra: test
Requires-Dist: pytest ; extra == 'test'
